simple_math/__init__.py
simple_math/math.py
simple_math_v1-1.2.0.dist-info/licenses/LICENSE
simple_math_v1-1.2.0.dist-info/METADATA
simple_math_v1-1.2.0.dist-info/WHEEL
simple_math_v1-1.2.0.dist-info/top_level.txt
simple_math_v1-1.2.0.dist-info/RECORD
