Metadata-Version: 2.4
Name: simple-math-v1
Version: 1.2.0
Summary: A simple Python package for basic mathematical operations
Author-email: Sarif Mia <sarifmia.ofc@gmail.com>
License: MIT
Project-URL: Homepage, https://github.com/sarifmia/simple-math
Project-URL: Repository, https://github.com/sarifmia/simple-math
Project-URL: Issues, https://github.com/sarifmia/simple-math/issues
Classifier: Development Status :: 5 - Production/Stable
Classifier: Intended Audience :: Developers
Classifier: License :: OSI Approved :: MIT License
Classifier: Programming Language :: Python :: 3
Classifier: Programming Language :: Python :: 3.6
Classifier: Programming Language :: Python :: 3.7
Classifier: Programming Language :: Python :: 3.8
Classifier: Programming Language :: Python :: 3.9
Classifier: Programming Language :: Python :: 3.10
Classifier: Programming Language :: Python :: 3.11
Requires-Python: >=3.6
License-File: LICENSE
Dynamic: license-file
